testops_pytest/__init__.py
testops_pytest/helper.py
testops_pytest/listener.py
testops_pytest-1.0.2.dist-info/LICENSE
testops_pytest-1.0.2.dist-info/METADATA
testops_pytest-1.0.2.dist-info/WHEEL
testops_pytest-1.0.2.dist-info/top_level.txt
testops_pytest-1.0.2.dist-info/RECORD
