Metadata-Version: 2.1
Name: testops-pytest
Version: 1.0.2
Summary: Katalon TestOps PyTest Plugin
Home-page: https://github.com/katalon-studio/testops-report-python
Author: Katalon, LLC. (https://www.katalon.io)
Author-email: info@katalon.io
License: UNKNOWN
Keywords: Katalon,TestOps
Platform: UNKNOWN
Classifier: Programming Language :: Python :: 3
Classifier: Operating System :: OS Independent
Requires-Python: >=3.6
Requires-Dist: testops-commons
